devtools/__init__.py
devtools/admin.py
devtools/apps.py
devtools/middleware.py
devtools/urls.py
devtools/utils.py
devtools/views.py
devtools/static/devtools/css/style.css
devtools/static/devtools/js/app.js
devtools/templates/devtools/base.html
devtools/templates/devtools/functions.html
devtools/templates/devtools/index.html
devtools/templates/devtools/query.html
devtools/templates/devtools/schema.html
devtools/templates/devtools/tables.html
devtools/templates/devtools/partials/stats_card.html
devtools/templatetags/__init__.py
devtools/templatetags/devtools_extras.py
django_devtools_local-1.1.1.dist-info/licenses/LICENSE
django_devtools_local-1.1.1.dist-info/METADATA
django_devtools_local-1.1.1.dist-info/WHEEL
django_devtools_local-1.1.1.dist-info/top_level.txt
django_devtools_local-1.1.1.dist-info/RECORD
